LICENSE
MANIFEST.in
README.rst
setup.cfg
setup.py
pywsse.egg-info/PKG-INFO
pywsse.egg-info/SOURCES.txt
pywsse.egg-info/dependency_links.txt
pywsse.egg-info/top_level.txt
wsse/__init__.py
wsse/compat.py
wsse/exceptions.py
wsse/settings.py
wsse/utc.py
wsse/utils.py
wsse/client/__init__.py
wsse/client/coreapi/__init__.py
wsse/client/coreapi/transport.py
wsse/client/coreapi/tests/__init__.py
wsse/client/coreapi/tests/test_transport.py
wsse/client/requests/__init__.py
wsse/client/requests/auth.py
wsse/client/requests/tests/__init__.py
wsse/client/requests/tests/test_auth.py
wsse/server/__init__.py
wsse/server/default/__init__.py
wsse/server/default/store.py
wsse/server/default/tests/__init__.py
wsse/server/default/tests/test_store.py
wsse/server/django/__init__.py
wsse/server/django/tests/__init__.py
wsse/server/django/tests/test_store.py
wsse/server/django/tests/urls.py
wsse/server/django/wsse/__init__.py
wsse/server/django/wsse/apps.py
wsse/server/django/wsse/models.py
wsse/server/django/wsse/store.py
wsse/server/django/wsse/migrations/0001_initial.py
wsse/server/django/wsse/migrations/0002_auto_20180501_0456.py
wsse/server/django/wsse/migrations/__init__.py
wsse/server/drf/__init__.py
wsse/server/drf/authentication.py
wsse/server/drf/tests/__init__.py
wsse/server/drf/tests/test_authentication.py
wsse/server/drf/tests/urls.py
wsse/server/drf/tests/views.py
wsse/tests/__init__.py
wsse/tests/settings.py
wsse/tests/test_utils.py
wsse/tests/urls.py